[
  {
    "Player": "Angkrish Raghuvanshi",
    "Team": "SoBo Mumbai Falcons",
    "DOB": "05/06/04",
    "Zodiac": "Gemini",
    "PredictionScale": 6
  },
  {
    "Player": "Kush Kariya",
    "Team": "SoBo Mumbai Falcons",
    "DOB": "09/08/04",
    "Zodiac": "Leo",
    "PredictionScale": 11
  },
  {
    "Player": "Ishan Mulchandani",
    "Team": "SoBo Mumbai Falcons",
    "DOB": "28/03/00",
    "Zodiac": "Aries",
    "PredictionScale": 3
  },
  {
    "Player": "Akash Parkar",
    "Team": "SoBo Mumbai Falcons",
    "DOB": "20/05/94",
    "Zodiac": "Taurus",
    "PredictionScale": 8
  },
  {
    "Player": "Vinayak Bhoir",
    "Team": "SoBo Mumbai Falcons",
    "DOB": "02/09/88",
    "Zodiac": "Virgo",
    "PredictionScale": 10
  },
  {
    "Player": "Harsh Aghav",
    "Team": "SoBo Mumbai Falcons",
    "DOB": "06/01/07",
    "Zodiac": "Capricorn",
    "PredictionScale": 12
  },
  {
    "Player": "Siddharth Raut",
    "Team": "SoBo Mumbai Falcons",
    "DOB": "24/06/93",
    "Zodiac": "Cancer",
    "PredictionScale": 2
  },
  {
    "Player": "Prathamesh Dake",
    "Team": "SoBo Mumbai Falcons",
    "DOB": "01/01/91",
    "Zodiac": "Capricorn",
    "PredictionScale": 12
  },
  {
    "Player": "Nikhil Giri ",
    "Team": "SoBo Mumbai Falcons",
    "DOB": "10/07/04",
    "Zodiac": "Cancer",
    "PredictionScale": 2
  },
  {
    "Player": "Amol Tarpure",
    "Team": "SoBo Mumbai Falcons",
    "DOB": "01/06/94",
    "Zodiac": "Gemini",
    "PredictionScale": 6
  },
  {
    "Player": "Mayuresh Tandel",
    "Team": "SoBo Mumbai Falcons",
    "DOB": "22/07/93",
    "Zodiac": "Cancer",
    "PredictionScale": 2
  },
  {
    "Player": "Shreyanssh Rai",
    "Team": "SoBo Mumbai Falcons",
    "DOB": "02/08/08",
    "Zodiac": "Leo",
    "PredictionScale": 11
  },
  {
    "Player": "Nishit Balla",
    "Team": "SoBo Mumbai Falcons",
    "DOB": "24/01/06",
    "Zodiac": "Aquarius",
    "PredictionScale": 4
  },
  {
    "Player": "Sai Chavan",
    "Team": "SoBo Mumbai Falcons",
    "DOB": "02/07/03",
    "Zodiac": "Cancer",
    "PredictionScale": 2
  },
  {
    "Player": "Prithvi Shaw",
    "Team": "North Mumbai Panthers",
    "DOB": "09/11/99",
    "Zodiac": "Scorpio",
    "PredictionScale": 9
  },
  {
    "Player": "Dharsh Murkute",
    "Team": "North Mumbai Panthers",
    "DOB": "04/06/07",
    "Zodiac": "Gemini",
    "PredictionScale": 6
  },
  {
    "Player": "Muzzamil Kadri",
    "Team": "North Mumbai Panthers",
    "DOB": "25/10/03",
    "Zodiac": "Scorpio",
    "PredictionScale": 9
  },
  {
    "Player": "Gaurav Jathar",
    "Team": "North Mumbai Panthers",
    "DOB": "30/01/91",
    "Zodiac": "Aquarius",
    "PredictionScale": 4
  },
  {
    "Player": "Sourabh Singh",
    "Team": "North Mumbai Panthers",
    "DOB": "21/11/02",
    "Zodiac": "Scorpio",
    "PredictionScale": 9
  },
  {
    "Player": "Ayush Vartak",
    "Team": "North Mumbai Panthers",
    "DOB": "29/10/04",
    "Zodiac": "Scorpio",
    "PredictionScale": 9
  },
  {
    "Player": "Alim Shaikh",
    "Team": "North Mumbai Panthers",
    "DOB": "07/06/98",
    "Zodiac": "Gemini",
    "PredictionScale": 6
  },
  {
    "Player": "Mohit Avasthi",
    "Team": "North Mumbai Panthers",
    "DOB": "18/11/92",
    "Zodiac": "Scorpio",
    "PredictionScale": 9
  },
  {
    "Player": "Prince Badiani",
    "Team": "North Mumbai Panthers",
    "DOB": "17/12/03",
    "Zodiac": "Sagittarius",
    "PredictionScale": 5
  },
  {
    "Player": "Divyansh Saxena",
    "Team": "North Mumbai Panthers",
    "DOB": "13/02/01",
    "Zodiac": "Aquarius",
    "PredictionScale": 4
  },
  {
    "Player": "Khizer Dafedar",
    "Team": "North Mumbai Panthers",
    "DOB": "10/10/97",
    "Zodiac": "Libra",
    "PredictionScale": 7
  },
  {
    "Player": "Abhigyan Kundu",
    "Team": "North Mumbai Panthers",
    "DOB": "30/04/08",
    "Zodiac": "Taurus",
    "PredictionScale": 8
  },
  {
    "Player": "Harshal Jadhav",
    "Team": "North Mumbai Panthers",
    "DOB": "16/10/01",
    "Zodiac": "Libra",
    "PredictionScale": 7
  },
  {
    "Player": "Pravesh Pal",
    "Team": "North Mumbai Panthers",
    "DOB": "27/03/03",
    "Zodiac": "Aries",
    "PredictionScale": 3
  },
  {
    "Player": "Pratik Mishra",
    "Team": "North Mumbai Panthers",
    "DOB": "25/01/01",
    "Zodiac": "Aquarius",
    "PredictionScale": 4
  },
  {
    "Player": "Tanush Kotian",
    "Team": "North Mumbai Panthers",
    "DOB": "16/10/98",
    "Zodiac": "Libra",
    "PredictionScale": 7
  }
]