[
  {
    "Player": "Angkrish Raghuvanshi",
    "Team": "SoBo Mumbai Falcons",
    "DOB": "05/06/04",
    "Zodiac": "Gemini",
    "PredictionScale": 7
  },
  {
    "Player": "Ishan Mulchandani",
    "Team": "SoBo Mumbai Falcons",
    "DOB": "28/03/00",
    "Zodiac": "Aries",
    "PredictionScale": 4
  },
  {
    "Player": "Shreyas Iyer",
    "Team": "SoBo Mumbai Falcons",
    "DOB": "06/12/94",
    "Zodiac": "Sagittarius",
    "PredictionScale": 6
  },
  {
    "Player": "Harsh Aghav",
    "Team": "SoBo Mumbai Falcons",
    "DOB": "06/01/07",
    "Zodiac": "Capricorn",
    "PredictionScale": 12
  },
  {
    "Player": "Akash Parkar",
    "Team": "SoBo Mumbai Falcons",
    "DOB": "20/05/94",
    "Zodiac": "Taurus",
    "PredictionScale": 9
  },
  {
    "Player": "Shreyanssh Rai",
    "Team": "SoBo Mumbai Falcons",
    "DOB": "02/08/08",
    "Zodiac": "Leo",
    "PredictionScale": 11
  },
  {
    "Player": "Siddharth Raut",
    "Team": "SoBo Mumbai Falcons",
    "DOB": "24/06/93",
    "Zodiac": "Cancer",
    "PredictionScale": 2
  },
  {
    "Player": "Nikhil Giri ",
    "Team": "SoBo Mumbai Falcons",
    "DOB": "10/07/04",
    "Zodiac": "Cancer",
    "PredictionScale": 2
  },
  {
    "Player": "Prathamesh Dake",
    "Team": "SoBo Mumbai Falcons",
    "DOB": "01/01/91",
    "Zodiac": "Capricorn",
    "PredictionScale": 12
  },
  {
    "Player": "Vinayak Bhoir",
    "Team": "SoBo Mumbai Falcons",
    "DOB": "02/09/88",
    "Zodiac": "Virgo",
    "PredictionScale": 10
  },
  {
    "Player": "Kush Kariya",
    "Team": "SoBo Mumbai Falcons",
    "DOB": "09/08/04",
    "Zodiac": "Leo",
    "PredictionScale": 11
  },
  {
    "Player": "Amol Tarpure",
    "Team": "SoBo Mumbai Falcons",
    "DOB": "01/06/94",
    "Zodiac": "Gemini",
    "PredictionScale": 7
  },
  {
    "Player": "Mayuresh Tandel",
    "Team": "SoBo Mumbai Falcons",
    "DOB": "22/07/93",
    "Zodiac": "Cancer",
    "PredictionScale": 2
  },
  {
    "Player": "Nishit Balla",
    "Team": "SoBo Mumbai Falcons",
    "DOB": "24/01/06",
    "Zodiac": "Aquarius",
    "PredictionScale": 5
  },
  {
    "Player": "Sai Chavan",
    "Team": "SoBo Mumbai Falcons",
    "DOB": "02/07/03",
    "Zodiac": "Cancer",
    "PredictionScale": 2
  },
  {
    "Player": "Suved Parkar",
    "Team": "NaMo Bandra Blasters",
    "DOB": "06/04/01",
    "Zodiac": "Aries",
    "PredictionScale": 4
  },
  {
    "Player": "Vikrant Auti",
    "Team": "NaMo Bandra Blasters",
    "DOB": "07/06/94",
    "Zodiac": "Gemini",
    "PredictionScale": 7
  },
  {
    "Player": "Tatsat Singh",
    "Team": "NaMo Bandra Blasters",
    "DOB": "03/10/03",
    "Zodiac": "Libra",
    "PredictionScale": 8
  },
  {
    "Player": "Shyamsundar Keshkamat",
    "Team": "NaMo Bandra Blasters",
    "DOB": "04/06/02",
    "Zodiac": "Gemini",
    "PredictionScale": 7
  },
  {
    "Player": "Karsh Kothari",
    "Team": "NaMo Bandra Blasters",
    "DOB": "29/02/96",
    "Zodiac": "Pisces",
    "PredictionScale": 3
  },
  {
    "Player": "Dhrumil Matkar",
    "Team": "NaMo Bandra Blasters",
    "DOB": "03/06/96",
    "Zodiac": "Gemini",
    "PredictionScale": 7
  },
  {
    "Player": "Sagarr Chhabriaa",
    "Team": "NaMo Bandra Blasters",
    "DOB": "12/01/00",
    "Zodiac": "Capricorn",
    "PredictionScale": 12
  },
  {
    "Player": "Dhanit Raut",
    "Team": "NaMo Bandra Blasters",
    "DOB": "07/09/01",
    "Zodiac": "Virgo",
    "PredictionScale": 10
  },
  {
    "Player": "Parth Ankolekar",
    "Team": "NaMo Bandra Blasters",
    "DOB": "14/04/06",
    "Zodiac": "Aries",
    "PredictionScale": 4
  },
  {
    "Player": "Royston Dias",
    "Team": "NaMo Bandra Blasters",
    "DOB": "30/01/93",
    "Zodiac": "Aquarius",
    "PredictionScale": 5
  },
  {
    "Player": "Ajinkya Rahane",
    "Team": "NaMo Bandra Blasters",
    "DOB": "06/06/88",
    "Zodiac": "Gemini",
    "PredictionScale": 7
  },
  {
    "Player": "Atif Attarwala",
    "Team": "NaMo Bandra Blasters",
    "DOB": "15/10/92",
    "Zodiac": "Libra",
    "PredictionScale": 8
  },
  {
    "Player": "Rahul Sawant",
    "Team": "NaMo Bandra Blasters",
    "DOB": "11/08/90",
    "Zodiac": "Leo",
    "PredictionScale": 11
  },
  {
    "Player": "Tushar Singh",
    "Team": "NaMo Bandra Blasters",
    "DOB": "25/09/99",
    "Zodiac": "Libra",
    "PredictionScale": 8
  },
  {
    "Player": "Naman Pushpak",
    "Team": "NaMo Bandra Blasters",
    "DOB": "18/02/06",
    "Zodiac": "Aquarius",
    "PredictionScale": 5
  },
  {
    "Player": "Rihit Patwal",
    "Team": "NaMo Bandra Blasters",
    "DOB": "17/01/01",
    "Zodiac": "Capricorn",
    "PredictionScale": 12
  }
]